pycount_caseexample/__init__.py
pycount_caseexample/data/__init__.py
pycount_caseexample/data/flatland.txt
pycount_caseexample/data/zen.txt
pycount_caseexample/datasets.py
pycount_caseexample/plotting.py
pycount_caseexample/pycount_caseexample.py
pycount_caseexample-0.6.26.dist-info/LICENSE
pycount_caseexample-0.6.26.dist-info/METADATA
pycount_caseexample-0.6.26.dist-info/WHEEL
pycount_caseexample-0.6.26.dist-info/RECORD
