Metadata-Version: 2.1
Name: pycount_caseexample
Version: 0.6.26
Summary: Counts the number of words in a file
License: MIT
Author: nobody
Requires-Python: >=3.9,<4
Classifier: License :: OSI Approved :: MIT License
Classifier: Programming Language :: Python :: 3
Classifier: Programming Language :: Python :: 3.9
Classifier: Programming Language :: Python :: 3.10
Classifier: Programming Language :: Python :: 3.11
Classifier: Programming Language :: Python :: 3.12
Classifier: Programming Language :: Python :: 3.13
Requires-Dist: matplotlib (>=3.9.2)
Requires-Dist: python-semantic-release (==9.9.0)
